django_hug/__init__.py
django_hug/arguments.py
django_hug/constants.py
django_hug/directives.py
django_hug/exceptions.py
django_hug/format.py
django_hug/routes.py
django_hug-0.1b2.dist-info/LICENSE.txt
django_hug-0.1b2.dist-info/METADATA
django_hug-0.1b2.dist-info/WHEEL
django_hug-0.1b2.dist-info/top_level.txt
django_hug-0.1b2.dist-info/RECORD
